main.py
einas_2.egg-info/PKG-INFO
einas_2.egg-info/SOURCES.txt
einas_2.egg-info/dependency_links.txt
einas_2.egg-info/top_level.txt