Metadata-Version: 2.1
Name: einas-2
Version: 2
Summary: This is a sample package generated with a common summary.
Home-page: UNKNOWN
License: UNKNOWN
Platform: UNKNOWN
